LICENSES.txt
setup.py
motus/__init__.py
motus/experimento.py
motus/funciones_auxiliares.py
motus/multiplies_experimentos.py
motus.egg-info/PKG-INFO
motus.egg-info/SOURCES.txt
motus.egg-info/dependency_links.txt
motus.egg-info/requires.txt
motus.egg-info/top_level.txt
motus/entropia_divergencia/__init__.py
motus/entropia_divergencia/entropia_aprox.py
motus/entropia_divergencia/entropia_aprox_agil.py
motus/entropia_divergencia/entropia_aprox_agil_generalizada.py
motus/entropia_divergencia/entropia_divergencia.py
motus/fisica_estadistica/__init__.py
motus/fisica_estadistica/histogramas.py
motus/fisica_estadistica/velocidad_aceleracion.py
motus/graficador/__init__.py
motus/graficador/cilindros.py
motus/graficador/config_graficas.py
motus/graficador/graficas_disponibles.py
motus/regiones_cuadriculadas/__init__.py
motus/regiones_cuadriculadas/matrices_recurrencia.py
motus/regiones_cuadriculadas/regiones_cuadriculadas.py
motus/regiones_cuadriculadas/regiones_preferidas.py
motus/regresion_lineal/__init__.py
motus/regresion_lineal/analisis_regresion_lineal.py
motus/regresion_lineal/distancias_pendientes.py
motus/rutas_distancias/__init__.py
motus/rutas_distancias/distancias.py
motus/rutas_distancias/rutas_vectoriales.py