Metadata-Version: 2.1
Name: motus
Version: 0.9.14.2
Summary: Paquetería para el Análisis Conductual de Patrones de Desplazamiento
Home-page: UNKNOWN
Author: Escamilla, Toledo, Tamayo, Avendanio, Leon, Eslava, Hernandez
Author-email: escamilla.een@gmail.com
License: UNKNOWN
Platform: UNKNOWN
License-File: LICENSES.txt
